common/__init__.py
common/appointment.py
common/config_loader.py
common/constants.py
common/cryptographer.py
common/db_manager.py
common/errors.py
common/exceptions.py
common/receipts.py
common/tools.py
teos/__init__.py
teos/api.py
teos/appointments_dbm.py
teos/block_processor.py
teos/builder.py
teos/carrier.py
teos/chain_monitor.py
teos/cleaner.py
teos/constants.py
teos/extended_appointment.py
teos/gatekeeper.py
teos/help.py
teos/inspector.py
teos/internal_api.py
teos/lightning_server.py
teos/logger.py
teos/responder.py
teos/rpc.py
teos/teosd.py
teos/tools.py
teos/users_dbm.py
teos/watcher.py
teos/cli/__init__.py
teos/cli/help.py
teos/cli/teos_cli.py
teos/protobuf/__init__.py
teos/protobuf/appointment_pb2.py
teos/protobuf/tower_services_pb2.py
teos/protobuf/tower_services_pb2_grpc.py
teos/protobuf/user_pb2.py
teos/utils/__init__.py
teos/utils/auth_proxy.py
teos/utils/rpc_errors.py
python_teos-0.1.1.dist-info/LICENSE
python_teos-0.1.1.dist-info/METADATA
python_teos-0.1.1.dist-info/WHEEL
python_teos-0.1.1.dist-info/entry_points.txt
python_teos-0.1.1.dist-info/top_level.txt
python_teos-0.1.1.dist-info/RECORD
